neocrym_sphinx_theme/__init__.py
neocrym_sphinx_theme/assets/scripts/gumshoe-patched.js
neocrym_sphinx_theme/assets/scripts/neocrym-sphinx-theme.js
neocrym_sphinx_theme/assets/styles/_neocrym.sass
neocrym_sphinx_theme/assets/styles/_scaffold.sass
neocrym_sphinx_theme/assets/styles/_shame.sass
neocrym_sphinx_theme/assets/styles/base/_index.sass
neocrym_sphinx_theme/assets/styles/base/_screen-readers.sass
neocrym_sphinx_theme/assets/styles/base/_theme.sass
neocrym_sphinx_theme/assets/styles/base/_typography.sass
neocrym_sphinx_theme/assets/styles/components/_footer.sass
neocrym_sphinx_theme/assets/styles/components/_index.sass
neocrym_sphinx_theme/assets/styles/components/_search.sass
neocrym_sphinx_theme/assets/styles/components/_sidebar.sass
neocrym_sphinx_theme/assets/styles/components/_table_of_contents.sass
neocrym_sphinx_theme/assets/styles/content/_admonitions.sass
neocrym_sphinx_theme/assets/styles/content/_api.sass
neocrym_sphinx_theme/assets/styles/content/_captions.sass
neocrym_sphinx_theme/assets/styles/content/_code.sass
neocrym_sphinx_theme/assets/styles/content/_footnotes.sass
neocrym_sphinx_theme/assets/styles/content/_gui-labels.sass
neocrym_sphinx_theme/assets/styles/content/_images.sass
neocrym_sphinx_theme/assets/styles/content/_index.sass
neocrym_sphinx_theme/assets/styles/content/_indexes.sass
neocrym_sphinx_theme/assets/styles/content/_lists.sass
neocrym_sphinx_theme/assets/styles/content/_math.sass
neocrym_sphinx_theme/assets/styles/content/_misc.sass
neocrym_sphinx_theme/assets/styles/content/_permalinks.sass
neocrym_sphinx_theme/assets/styles/content/_rubrics.sass
neocrym_sphinx_theme/assets/styles/content/_sidebar.sass
neocrym_sphinx_theme/assets/styles/content/_tables.sass
neocrym_sphinx_theme/assets/styles/extensions/_copybutton.sass
neocrym_sphinx_theme/assets/styles/extensions/_index.sass
neocrym_sphinx_theme/assets/styles/extensions/_readthedocs.sass
neocrym_sphinx_theme/assets/styles/extensions/_sphinx-design.sass
neocrym_sphinx_theme-0.1.4.dist-info/LICENSE
neocrym_sphinx_theme-0.1.4.dist-info/METADATA
neocrym_sphinx_theme-0.1.4.dist-info/WHEEL
neocrym_sphinx_theme-0.1.4.dist-info/entry_points.txt
neocrym_sphinx_theme-0.1.4.dist-info/RECORD